regen-docs
setup.cfg
setup.py
INITools.egg-info/PKG-INFO
INITools.egg-info/SOURCES.txt
INITools.egg-info/dependency_links.txt
INITools.egg-info/top_level.txt
INITools.egg-info/zip-safe
docs/conf.py
docs/index.txt
docs/modules/configparser.txt
docs/modules/iniparser.txt
docs/modules/lazyiniparser.txt
initools/__init__.py
initools/_setmixin.py
initools/configparser.py
initools/configwrapper.py
initools/iniparser.py
initools/inischema.py
initools/lazyiniparser.py
initools/lazyloader.py
initools/nested.py
tests/cfgparser.1
tests/conftest.py
tests/test_cfgparser.py
tests/test_iniparser.py
tests/test_inischema.py
tests/test_lazyiniparser.py
tests/test_lazyloader.py
tests/test_nested.py