Metadata-Version: 1.0
Name: INITools
Version: 0.3
Summary: Tools for parsing and using INI-style files
Home-page: http://pythonpaste.org/initools/
Author: Ian Bicking
Author-email: ianb@colorstudy.com
License: MIT
Keywords: config parser ini
Platform: UNKNOWN
Classifier: Intended Audience :: Developers
Classifier: License :: OSI Approved :: MIT License
Classifier: Topic :: Software Development :: Libraries
